Metadata-Version: 1.0
Name: wsgitemplates
Version: 0.2.1
Summary: A series of templates for use in creating WSGI applications
Home-page: http://code.google.com/p/wsgitemplates
Author: Matthew Wilkes
Author-email: matt@matthewwilkes.name
License: BSD
Keywords: wsgi template paste
Platform: UNKNOWN
